README.md
README.rst
setup.py
src/flake8_rst_docparams/__init__.py
src/flake8_rst_docparams/check_params.py
src/flake8_rst_docparams.egg-info/PKG-INFO
src/flake8_rst_docparams.egg-info/SOURCES.txt
src/flake8_rst_docparams.egg-info/dependency_links.txt
src/flake8_rst_docparams.egg-info/entry_points.txt
src/flake8_rst_docparams.egg-info/top_level.txt