Metadata-Version: 2.1
Name: flake8-rst-docparams
Version: 1.0.7
Summary: Check for reStructuredText function parameter documentation
Home-page: https://bitbucket.org/jakobsg/flake8-rst-docparams
Author: Jakob Simon-Gaarde
Author-email: jakobsg@gmail.com
Classifier: Intended Audience :: Developers
Classifier: Framework :: Flake8
Classifier: Programming Language :: Python :: 3
Classifier: Operating System :: OS Independent
Classifier: License :: OSI Approved :: MIT License
Classifier: Topic :: Software Development :: Libraries :: Python Modules
Classifier: Topic :: Software Development :: Quality Assurance
